markup_parser/__init__.py
markup_parser/markup_parser.cpython-39-darwin.so
markup_parser/parser.py
markup_parser-0.1.3.dist-info/LICENSE
markup_parser-0.1.3.dist-info/METADATA
markup_parser-0.1.3.dist-info/WHEEL
markup_parser-0.1.3.dist-info/top_level.txt
markup_parser-0.1.3.dist-info/RECORD
