Metadata-Version: 2.1
Name: markup-parser
Version: 0.1.3
Summary: Parse JS variables from HTML markup
Home-page: https://github.com/bigpe/markup-parser
Author: Aleskandr Sokolov
Author-email: bigpewm@gmail.com
License: MIT
Keywords: html,parse,markup,js,variables,rust
Platform: any
Classifier: Development Status :: 3 - Alpha
Classifier: Intended Audience :: Developers
Classifier: License :: OSI Approved :: MIT License
Classifier: Operating System :: OS Independent
Classifier: Programming Language :: Python
Classifier: Programming Language :: Python :: 3.6
Classifier: Programming Language :: Python :: 3.7
Classifier: Programming Language :: Python :: 3.8
Classifier: Programming Language :: Python :: 3.9
Classifier: Programming Language :: Python :: 3.10
Classifier: Topic :: Software Development :: Libraries :: Python Modules
Requires-Python: >=3.6.0
License-File: LICENSE
